.gitignore
.pep8speaks.yml
.pyup.yml
.travis.yml
LICENSE
README.md
requirements.txt
setup.py
tox.ini
docs/Makefile
docs/api.rst
docs/conf.py
docs/index.rst
docs/make.bat
docs/_static/donotdelete
docs/api/stats.rst
docs/api/tensor.rst
docs/api/stats/distance.rst
docs/api/tensor/allele_counts.rst
docs/api/tensor/genotypes.rst
docs/api/tensor/haplotypes.rst
docs/api/tensor/selections.rst
docs/api/tensor/variants.rst
src/skallel/__init__.py
src/skallel/version.py
src/skallel.egg-info/PKG-INFO
src/skallel.egg-info/SOURCES.txt
src/skallel.egg-info/dependency_links.txt
src/skallel.egg-info/not-zip-safe
src/skallel.egg-info/requires.txt
src/skallel.egg-info/top_level.txt
src/skallel/test/__init__.py
src/skallel/test/test_namespace.py